{
  "uid": "ba725eccd92a",
  "name": "Daily Challenge 2028-04-26",
  "width": 5,
  "height": 5,
  "clues": [
    [
      0,
      1,
      2,
      3,
      3
    ],
    [
      3,
      4,
      4,
      4,
      3
    ],
    [
      3,
      5,
      4,
      5,
      3
    ],
    [
      5,
      8,
      5,
      5,
      1
    ],
    [
      3,
      5,
      3,
      4,
      1
    ]
  ],
  "solution": [
    [
      1,
      0,
      0,
      1,
      1
    ],
    [
      0,
      0,
      0,
      1,
      1
    ],
    [
      1,
      1,
      1,
      0,
      0
    ],
    [
      1,
      1,
      1,
      0,
      1
    ],
    [
      1,
      1,
      1,
      0,
      1
    ]
  ],
  "logical_steps": 11,
  "date": "2028-04-26"
}