{
  "uid": "9b5b889752ce",
  "name": "Daily Challenge 2029-05-19",
  "width": 5,
  "height": 5,
  "clues": [
    [
      1,
      3,
      2,
      4,
      2
    ],
    [
      3,
      6,
      3,
      4,
      2
    ],
    [
      4,
      6,
      5,
      6,
      4
    ],
    [
      3,
      4,
      5,
      3,
      2
    ],
    [
      2,
      2,
      3,
      2,
      3
    ]
  ],
  "solution": [
    [
      1,
      0,
      0,
      0,
      1
    ],
    [
      1,
      0,
      1,
      1,
      1
    ],
    [
      1,
      1,
      1,
      0,
      0
    ],
    [
      1,
      1,
      0,
      1,
      1
    ],
    [
      0,
      0,
      0,
      1,
      0
    ]
  ],
  "logical_steps": 10,
  "date": "2029-05-19"
}