{
  "uid": "9e3323c78dcd",
  "name": "Daily Challenge 2032-07-16",
  "width": 5,
  "height": 5,
  "clues": [
    [
      2,
      3,
      3,
      3,
      1
    ],
    [
      2,
      3,
      3,
      3,
      0
    ],
    [
      1,
      3,
      4,
      4,
      2
    ],
    [
      2,
      3,
      2,
      2,
      2
    ],
    [
      1,
      2,
      3,
      3,
      1
    ]
  ],
  "solution": [
    [
      0,
      1,
      1,
      0,
      0
    ],
    [
      0,
      1,
      1,
      0,
      1
    ],
    [
      0,
      0,
      0,
      0,
      0
    ],
    [
      0,
      0,
      1,
      1,
      0
    ],
    [
      1,
      1,
      0,
      0,
      1
    ]
  ],
  "logical_steps": 13,
  "date": "2032-07-16"
}